{
  "items": [
    {
      "description": "",
      "items": [
        {
          "children": [],
          "description": null,
          "title": "GitHub",
          "repo_info": {
            "archived": false,
            "language": "JavaScript",
            "last_commit": "2026-02-13T03:38:41Z",
            "owner": "vercel",
            "repo": "next.js",
            "stars": 137647
          }
        },
        {
          "children": [],
          "description": null,
          "title": "GitHub discussions for Next.js",
          "repo_info": {
            "archived": false,
            "language": "JavaScript",
            "last_commit": "2026-02-13T03:38:41Z",
            "owner": "vercel",
            "repo": "next.js",
            "stars": 137647
          }
        },
        {
          "children": [],
          "description": null,
          "title": "Vercel Community"
        }
      ],
      "title": "Community"
    },
    {
      "description": "",
      "items": [
        {
          "children": [],
          "description": "Power packed Next.js and Tailwind CSS template. Built with developer experience in mind. Contains Husky, CommitLint, Prettier, Eslint etc. configs. ✨",
          "title": "Kaminari Template"
        },
        {
          "children": [],
          "description": "A modern portfolio starter with Next.js, Strapi, and Tailwind CSS, featuring automated XML sitemap, JSON-LD schemas, OpenGraph metadata, and a contact form with spam protection.",
          "title": "Next.js, Strapi Portfolio Starter",
          "repo_info": {
            "archived": false,
            "language": "JavaScript",
            "last_commit": "2026-01-08T09:43:02Z",
            "owner": "PictureElement",
            "repo": "nextjs-strapi-portfolio-starter",
            "stars": 23
          }
        },
        {
          "children": [],
          "description": "Next.js static blog powered by the Cosmic Headless CMS",
          "title": "Next.js Static Blog"
        },
        {
          "children": [],
          "description": null,
          "title": "NextJS Headless CMS Powered Blog Starter",
          "repo_info": {
            "archived": false,
            "language": "JavaScript",
            "last_commit": "2023-04-18T06:54:01Z",
            "owner": "ButterCMS",
            "repo": "react-cms-blog-with-next-js",
            "stars": 145
          }
        },
        {
          "children": [],
          "description": "Deploy a Next.js App to AWS Lambda using Apex Up.",
          "title": "Next.js App with AWS Lambda",
          "repo_info": {
            "archived": false,
            "language": "JavaScript",
            "last_commit": "2019-04-11T14:40:51Z",
            "owner": "mattdamon108",
            "repo": "nextjs-with-lambda",
            "stars": 59
          }
        },
        {
          "children": [],
          "description": "An Example of a PWA using Nextjs, Material-UI, Typescript and Auth0 💗",
          "title": "Nitro 🚀",
          "repo_info": {
            "archived": false,
            "language": "TypeScript",
            "last_commit": "2026-02-12T11:50:25Z",
            "owner": "williamluke4",
            "repo": "nitro",
            "stars": 284
          }
        },
        {
          "children": [],
          "description": "Serverless, Typescript, Jest, Github CI, SCSS, prettier boilerplate",
          "title": "Next & Now 2.0 Typescript template",
          "repo_info": {
            "archived": false,
            "language": "TypeScript",
            "last_commit": "2022-02-10T19:13:27Z",
            "owner": "alepacheco",
            "repo": "landing-template",
            "stars": 43
          }
        },
        {
          "children": [],
          "description": "Flexible  with Next.js 9 and Vercel, with pre-configured Sentry, cookies, Amplitude, Emotion, FontAwesome, GraphQL/GraphCMS (Apollo), Bootstrap (Reactstrap), i18next (Locize), Jest, Cypress (E2E tests) and CI/CD (GH Actions), with full TypeScript support and",
          "title": "Next Right Now",
          "repo_info": {
            "archived": false,
            "language": "HTML",
            "last_commit": "2023-10-29T18:15:29Z",
            "owner": "UnlyEd",
            "repo": "next-right-now",
            "stars": 1280
          }
        },
        {
          "children": [],
          "description": "React + GraphQL + Next.js + Apollo + Scss + Typescript + Prettier & EsLint boilerplate",
          "title": "Next Graphql Apollo Typescript_Boostrap - Pobocha",
          "repo_info": {
            "archived": false,
            "language": "TypeScript",
            "last_commit": "2023-06-19T12:53:02Z",
            "owner": "Sebastp",
            "repo": "Next-react-graphql-apollo_Boostrap",
            "stars": 88
          }
        },
        {
          "children": [],
          "description": "Serverless, Typescript, Jest, Github CI, SCSS, prettier boilerplate",
          "title": "Next & Vercel Typescript template",
          "repo_info": {
            "archived": false,
            "language": "TypeScript",
            "last_commit": "2022-02-10T19:13:27Z",
            "owner": "alepacheco",
            "repo": "landing-template",
            "stars": 43
          }
        },
        {
          "children": [],
          "description": "Hosting NextJS app with Bootstrap in Firebase with Cloud Functions.",
          "title": "NextJS in Firebase with Bootstrap",
          "repo_info": {
            "archived": false,
            "language": "JavaScript",
            "last_commit": "2017-12-24T01:09:52Z",
            "owner": "ananddayalan",
            "repo": "nextjs-in-firebase-with-bootstrap",
            "stars": 25
          }
        },
        {
          "children": [],
          "description": "Simple PWA boilerplate with Next.js and Redux.",
          "title": "Next Simple Starter",
          "repo_info": {
            "archived": false,
            "language": "JavaScript",
            "last_commit": "2026-01-28T17:54:56Z",
            "owner": "ooade",
            "repo": "NextSimpleStarter",
            "stars": 951
          }
        },
        {
          "children": [],
          "description": "Starter project for Next.js with and email and oAuth authentication.",
          "title": "NextJS Starter",
          "repo_info": {
            "archived": true,
            "language": "JavaScript",
            "last_commit": "2020-07-15T00:01:03Z",
            "owner": "iaincollins",
            "repo": "nextjs-starter",
            "stars": 1366
          }
        },
        {
          "children": [],
          "description": "An SEO Optimized Next.js 10 starter kit template with React 17 + Typescript + Tailwind CSS 2 + React Query 3 + (GitHub Auth + Passwordless Auth) using (NextAuth.js and Fauna DB), ESLint, Prettier, Pre-commit hook with Husky. Can have different layouts for different pages.",
          "title": "nextjs-starter",
          "repo_info": {
            "archived": false,
            "language": "JavaScript",
            "last_commit": "2021-09-01T06:10:36Z",
            "owner": "pbteja1998",
            "repo": "nextjs-starter",
            "stars": 453
          }
        },
        {
          "children": [],
          "description": "Production-ready boilerplate with support for GraphQL, SSR, Hot-reload, CSS-in-JS, caching, and more.",
          "title": "RAN!",
          "repo_info": {
            "archived": false,
            "language": "JavaScript",
            "last_commit": "2026-01-24T09:13:02Z",
            "owner": "sly777",
            "repo": "ran",
            "stars": 2208
          }
        },
        {
          "children": [],
          "description": "Simple Markdown based blog built with Next.js with static exports.",
          "title": "Next Simple Blog",
          "repo_info": {
            "archived": false,
            "language": "JavaScript",
            "last_commit": "2022-12-22T02:36:32Z",
            "owner": "tscanlin",
            "repo": "next-blog",
            "stars": 555
          }
        },
        {
          "children": [],
          "description": "Create a static photo blog.",
          "title": "phox",
          "repo_info": {
            "archived": true,
            "language": "TypeScript",
            "last_commit": "2019-07-28T09:06:39Z",
            "owner": "herschel666",
            "repo": "phox",
            "stars": 19
          }
        },
        {
          "children": [],
          "description": "Boilerplate for a full stack app built using Next, Express, react-bootstrap, SCSS and SSR with eslint.",
          "title": "Next Express Bootstrap Boilerplate",
          "repo_info": {
            "archived": false,
            "language": "JavaScript",
            "last_commit": "2022-01-02T15:48:59Z",
            "owner": "MustansirZia",
            "repo": "next-express-bootstrap-boilerplate",
            "stars": 113
          }
        },
        {
          "children": [],
          "description": "Blog with simple CMS built with Next.js, Firebase Firestore, styled-components and mobx-state-tree.",
          "title": "Next Blog Firestore",
          "repo_info": {
            "archived": false,
            "language": "JavaScript",
            "last_commit": "2018-10-25T07:41:34Z",
            "owner": "suevalov",
            "repo": "next-blog-firestore",
            "stars": 270
          }
        },
        {
          "children": [],
          "description": "Next.js starter with Express, Redux, and PostCSS.",
          "title": "Next Redux Starter",
          "repo_info": {
            "archived": false,
            "language": "JavaScript",
            "last_commit": "2022-12-10T17:13:27Z",
            "owner": "CodementorIO",
            "repo": "nextjs-redux-starter",
            "stars": 376
          }
        },
        {
          "children": [],
          "description": "A boilerplate NextJS with Redux and Material UI.",
          "title": "NextJS Redux-Wrapper Material-UI",
          "repo_info": {
            "archived": true,
            "language": "JavaScript",
            "last_commit": "2023-10-08T21:05:05Z",
            "owner": "joaopaulomoraes",
            "repo": "nextjs-with-redux-and-material-ui",
            "stars": 131
          }
        },
        {
          "children": [],
          "description": "Actively maintained Next.js components library  minimal boilerplate to rapidly get staarted with app with working user accounts based on Ooth.",
          "title": "Staart",
          "repo_info": {
            "archived": true,
            "language": "TypeScript",
            "last_commit": "2019-03-19T14:24:09Z",
            "owner": "nmaro",
            "repo": "staart",
            "stars": 314
          }
        },
        {
          "children": [],
          "description": "tada: TypeScript + NextJS, Styled-jsx, Redux, PostCSS, configurable SEO",
          "title": "NextJS TypeScript Starter Kit",
          "repo_info": {
            "archived": true,
            "language": "TypeScript",
            "last_commit": "2019-04-24T19:36:42Z",
            "owner": "deptno",
            "repo": "next.js-typescript-starter-kit",
            "stars": 337
          }
        },
        {
          "children": [],
          "description": "External CSS and Sass + Importing images from anywhere + Prettier and Eslint + Environment variables and many more features.",
          "title": "Next Boilerplate"
        },
        {
          "children": [],
          "description": "A full and simple boilerplate with  and built in.",
          "title": "next-starter",
          "repo_info": {
            "archived": false,
            "language": "JavaScript",
            "last_commit": "2023-01-04T21:41:47Z",
            "owner": "YuriBrunetto",
            "repo": "next-starter",
            "stars": 27
          }
        },
        {
          "children": [],
          "description": "A minimalistic next.js + typescript monorepo.",
          "title": "Typescript Monorepo Next Example",
          "repo_info": {
            "archived": false,
            "language": "TypeScript",
            "last_commit": "2018-08-15T06:19:32Z",
            "owner": "deptno",
            "repo": "typescript-monorepo-next-example",
            "stars": 44
          }
        },
        {
          "children": [],
          "description": "A minimal starter/demo with basic CRUD, axios/localstorage, MobX, SASS, static site export, live demo",
          "title": "tomimick/tm-nextjs-starter",
          "repo_info": {
            "archived": false,
            "language": "JavaScript",
            "last_commit": "2023-01-04T10:24:19Z",
            "owner": "tomimick",
            "repo": "tm-nextjs-starter",
            "stars": 50
          }
        },
        {
          "children": [],
          "description": "A minimal boilerplate with redux, styled-components, material-ui and typescript with a custom express server.",
          "title": "csprance/next-smrt",
          "repo_info": {
            "archived": false,
            "language": "TypeScript",
            "last_commit": "2023-01-07T16:29:14Z",
            "owner": "csprance",
            "repo": "next-smrt",
            "stars": 56
          }
        },
        {
          "children": [],
          "description": "An Electron with Next.js apps generator ⚡",
          "title": "Nextron",
          "repo_info": {
            "archived": false,
            "language": "TypeScript",
            "last_commit": "2026-02-07T10:33:22Z",
            "owner": "saltyshiomix",
            "repo": "nextron",
            "stars": 4384
          }
        },
        {
          "children": [],
          "description": "A well-structured production ready Next.js boilerplate with Typescript, Redux, Express.js, Sass, Css, EnvConfig, Reverse Proxy, Bundle",
          "title": "next-boilerplate",
          "repo_info": {
            "archived": false,
            "language": "TypeScript",
            "last_commit": "2023-08-04T17:07:57Z",
            "owner": "pankod",
            "repo": "next-boilerplate",
            "stars": 1614
          }
        },
        {
          "children": [],
          "description": "Full stack web application skeleton (Next.js, Redux, RxJS, Immutable, Express)",
          "title": "Oh My Fullstack",
          "repo_info": {
            "archived": false,
            "language": "JavaScript",
            "last_commit": "2023-03-04T04:14:42Z",
            "owner": "oh-my-c0de",
            "repo": "oh-my-fullstack",
            "stars": 174
          }
        },
        {
          "children": [],
          "description": "Forum-like fullstack web app with Next 7.0.2 + Sequelize 4/Postgres + Typescript + Redux + Passport Local Auth + Emotion",
          "title": "Next-Postgres-With-Typescript",
          "repo_info": {
            "archived": false,
            "language": "TypeScript",
            "last_commit": "2019-03-16T17:46:31Z",
            "owner": "brandontle",
            "repo": "next-postgres-with-typescript",
            "stars": 21
          }
        },
        {
          "children": [],
          "description": "An application skeleton for those who want to transpile their Express as well as their Next.js code using Babel.",
          "title": "Next.js with Express and Babel",
          "repo_info": {
            "archived": true,
            "language": "JavaScript",
            "last_commit": "2019-03-07T12:38:27Z",
            "owner": "pd-smith",
            "repo": "next-express-babel",
            "stars": 3
          }
        },
        {
          "children": [],
          "description": "Create SSR Next.js websites using GraphQL with Postgres (Next.js, Postgres, GraphQL)",
          "title": "next-postgres-graphql",
          "repo_info": {
            "archived": false,
            "language": "TypeScript",
            "last_commit": "2026-02-12T16:26:49Z",
            "owner": "hasura",
            "repo": "graphql-engine",
            "stars": 31899
          }
        },
        {
          "children": [],
          "description": "Full-fledged app made with Next.JS and MongoDB, with authentication and much more (Next.js 9, MongoDB)",
          "title": "nextjs-mongodb-app",
          "repo_info": {
            "archived": false,
            "language": "JavaScript",
            "last_commit": "2024-03-20T03:28:34Z",
            "owner": "hoangvvo",
            "repo": "nextjs-mongodb-app",
            "stars": 1562
          }
        },
        {
          "children": [],
          "description": "rocket: A basis for reducing the configuration of your projects with nextJS, best development practices and popular libraries in the developer community.",
          "title": "react-next-boilerplate",
          "repo_info": {
            "archived": true,
            "language": "JavaScript",
            "last_commit": "2024-09-17T05:18:21Z",
            "owner": "react-next-boilerplate",
            "repo": "react-next-boilerplate",
            "stars": 364
          }
        },
        {
          "children": [],
          "description": "typescript + redux + styled-components + react-testing-library + eslint + fontawesome",
          "title": "The-Nextjs-starter",
          "repo_info": {
            "archived": false,
            "language": "TypeScript",
            "last_commit": "2023-01-08T23:50:11Z",
            "owner": "novellito",
            "repo": "the-nextjs-starter",
            "stars": 22
          }
        },
        {
          "children": [],
          "description": "Full stack boilerplate/hackathon starter with: PostgreSQL, Knex.js, NestJS, Next.js (obviously), GraphQL, React (with hooks and typescript), Material-UI, Docker multistage images for, Docker compose and a Gitlab CI/CD pipeline fully configured.",
          "title": "The Knests Stack",
          "repo_info": {
            "archived": false,
            "language": "TypeScript",
            "last_commit": "2026-02-11T13:31:24Z",
            "owner": "tudorconstantin",
            "repo": "knests",
            "stars": 350
          }
        },
        {
          "children": [],
          "description": "A Medium-inspired dev blog starter built with Next.js, React, and TypeScript, with Markdown rendering, syntax highlighting, SEO/meta tags, and RSS feed generation out of the box.",
          "title": "Devii",
          "repo_info": {
            "archived": true,
            "language": "TypeScript",
            "last_commit": "2023-06-22T22:38:18Z",
            "owner": "vriad",
            "repo": "devii",
            "stars": 498
          }
        },
        {
          "children": [],
          "description": "The perfect starter code for your blog based on Next.js framework. ⚡️ Made with Next.js, TypeScript, ESLint, Prettier, PostCSS, Tailwind CSS.",
          "title": "Nextjs Blog Starter"
        },
        {
          "children": [],
          "description": "A perfect boilerplate for building a blog website on Netlify stacks with standard features like tagging, CMS, and shortcodes.",
          "title": "Next.js and Netlify Blogging Template",
          "repo_info": {
            "archived": false,
            "language": "TypeScript",
            "last_commit": "2023-10-05T18:26:18Z",
            "owner": "wutali",
            "repo": "nextjs-netlify-blog-template",
            "stars": 472
          }
        },
        {
          "children": [],
          "description": "GraphQL Apollo Client-Server integration in Next.js with Nexus Schema (Code first approach).",
          "title": "Nextjs Apollo Nexus",
          "repo_info": {
            "archived": false,
            "language": "TypeScript",
            "last_commit": "2020-09-03T07:17:28Z",
            "owner": "inblack67",
            "repo": "GraphQL-Next-Setup",
            "stars": 3
          }
        },
        {
          "children": [],
          "description": "Beautiful Nextjs portfolio starter for software engineers and designers to show work they're so proud of.",
          "title": "Nextjs Starter Peacock",
          "repo_info": {
            "archived": false,
            "language": "TypeScript",
            "last_commit": "2024-03-09T20:00:41Z",
            "owner": "vickOnRails",
            "repo": "next-starter-peacock",
            "stars": 132
          }
        },
        {
          "children": [],
          "description": "Static website multi-language boilerplate with user-editable pages and navigation using Netlify CMS + Next.js + SCSS + Typescript.",
          "title": "Nextatic",
          "repo_info": {
            "archived": false,
            "language": "TypeScript",
            "last_commit": "2020-12-06T20:32:57Z",
            "owner": "tancredi",
            "repo": "nextatic",
            "stars": 48
          }
        },
        {
          "children": [],
          "description": "An additional server on express that runs alongside nextjs and regenerates sitemap ( with index sitemap ) and robots.txt files on request from STR API.",
          "title": "Sitemap generator for NextJS & StrAPI",
          "repo_info": {
            "archived": false,
            "language": "JavaScript",
            "last_commit": "2021-01-19T20:07:39Z",
            "owner": "stovv",
            "repo": "next-strapi-sitemap",
            "stars": 6
          }
        },
        {
          "children": [],
          "description": "superplate creates Next.js app in seconds with TypeScript, styled-components, SWR, Storybook, and 35+ plugin.",
          "title": "superplate",
          "repo_info": {
            "archived": false,
            "language": "TypeScript",
            "last_commit": "2025-08-28T11:20:28Z",
            "owner": "pankod",
            "repo": "superplate",
            "stars": 2895
          }
        },
        {
          "children": [],
          "description": "Hydrogen is a Nextjs blog starter template build with tailwindCss and MDX supports. It has all necessary MDX shortcodes out of the box.",
          "title": "Hydrogen"
        },
        {
          "children": [],
          "description": "A awesome boilerplate for startup application with authentication using Next.js + Typescript + Tailwind CSS + Firebase-auth + React-Firebase-Hooks",
          "title": "Next-Fire-Auth",
          "repo_info": {
            "archived": false,
            "language": "TypeScript",
            "last_commit": "2023-01-04T19:18:55Z",
            "owner": "hrushikedar33",
            "repo": "next-fire-auth",
            "stars": 7
          }
        },
        {
          "children": [],
          "description": "A Chargebee focused T3 Stack that integrates User Subscriptions, Authentication and Testing. Driven by Prisma ORM.",
          "title": "NextJS Chargebee Subscription",
          "repo_info": {
            "archived": false,
            "language": "TypeScript",
            "last_commit": "2023-03-09T19:05:30Z",
            "owner": "bharathvaj-ganesan",
            "repo": "chargebee-saas-stack",
            "stars": 20
          }
        },
        {
          "children": [],
          "description": "enterprise-grade boilerplate for high-performance, maintainable apps. Built with Tailwind CSS, RadixUI, TypeScript and more.",
          "title": "Next.js Enterprise",
          "repo_info": {
            "archived": false,
            "language": "TypeScript",
            "last_commit": "2026-02-12T11:41:21Z",
            "owner": "Blazity",
            "repo": "next-enterprise",
            "stars": 7333
          }
        },
        {
          "children": [],
          "description": "opinionated UI starter with TypeScript, React, NextJS, Chakra UI, tRPC, Prisma, TanStack Query, Storybook, Playwright, Formiz",
          "title": "Start UI [web]",
          "repo_info": {
            "archived": false,
            "language": "TypeScript",
            "last_commit": "2026-02-12T19:52:36Z",
            "owner": "BearStudio",
            "repo": "start-ui-web",
            "stars": 1681
          }
        }
      ],
      "title": "Boilerplates"
    },
    {
      "description": "",
      "items": [
        {
          "children": [],
          "description": "Language detector that works universally (browser + server) - Meant to be used with a universal framework, such as Next.js",
          "title": "Next universal language detector",
          "repo_info": {
            "archived": false,
            "language": "TypeScript",
            "last_commit": "2020-04-23T13:09:29Z",
            "owner": "UnlyEd",
            "repo": "universal-language-detector",
            "stars": 98
          }
        },
        {
          "children": [],
          "description": "Universal named routes for Next.js.",
          "title": "Next Routes",
          "repo_info": {
            "archived": false,
            "language": "JavaScript",
            "last_commit": "2024-08-06T05:50:49Z",
            "owner": "fridays",
            "repo": "next-routes",
            "stars": 2468
          }
        },
        {
          "children": [],
          "description": "Extended Next.js server with  support.",
          "title": "Next-Pkg",
          "repo_info": {
            "archived": true,
            "language": "JavaScript",
            "last_commit": "2022-11-05T14:36:57Z",
            "owner": "onready",
            "repo": "next-pkg",
            "stars": 66
          }
        },
        {
          "children": [],
          "description": "Next.js plugin for .graphql and .gql files using graphql-tag",
          "title": "Next Plugin Graphql",
          "repo_info": {
            "archived": false,
            "language": "JavaScript",
            "last_commit": "2023-02-24T04:57:16Z",
            "owner": "lfades",
            "repo": "next-plugin-graphql",
            "stars": 58
          }
        },
        {
          "children": [],
          "description": "Apollo Graphql integration for Next.js",
          "title": "Next With Apollo",
          "repo_info": {
            "archived": false,
            "language": "TypeScript",
            "last_commit": "2024-02-24T17:09:28Z",
            "owner": "lfades",
            "repo": "next-with-apollo",
            "stars": 764
          }
        },
        {
          "children": [],
          "description": "SEO made easy for Next.js",
          "title": "Next SEO",
          "repo_info": {
            "archived": false,
            "language": "TypeScript",
            "last_commit": "2026-01-27T20:28:36Z",
            "owner": "garmeeh",
            "repo": "next-seo",
            "stars": 8286
          }
        },
        {
          "children": [],
          "description": "Sitemap generator for Next.js",
          "title": "Next-Sitemap",
          "repo_info": {
            "archived": false,
            "language": "TypeScript",
            "last_commit": "2026-02-02T01:55:44Z",
            "owner": "iamvishnusankar",
            "repo": "next-sitemap",
            "stars": 3698
          }
        },
        {
          "children": [],
          "description": "UserAgent parser for Next.js",
          "title": "Next UserAgent"
        },
        {
          "children": [],
          "description": "Cookie serializer and deserializer library for Next.js.",
          "title": "Next Cookie"
        },
        {
          "children": [],
          "description": "A static site generator based in Next.js.",
          "title": "Nextein",
          "repo_info": {
            "archived": true,
            "language": "JavaScript",
            "last_commit": "2023-05-31T14:23:31Z",
            "owner": "elmasse",
            "repo": "nextein",
            "stars": 892
          }
        },
        {
          "children": [],
          "description": "Easily add a blog to any next.js based project",
          "title": "next-mdx-blog",
          "repo_info": {
            "archived": false,
            "language": "JavaScript",
            "last_commit": "2022-12-08T19:14:53Z",
            "owner": "hipstersmoothie",
            "repo": "next-mdx-blog",
            "stars": 73
          }
        },
        {
          "children": [],
          "description": "The easiest way to translate your NextJs apps.",
          "title": "next-i18next",
          "repo_info": {
            "archived": false,
            "language": "TypeScript",
            "last_commit": "2026-01-05T11:20:44Z",
            "owner": "isaachinman",
            "repo": "next-i18next",
            "stars": 6124
          }
        },
        {
          "children": [],
          "description": "A NextJS routing middleware",
          "title": "next-routes-middleware",
          "repo_info": {
            "archived": false,
            "language": "JavaScript",
            "last_commit": "2025-04-05T23:17:57Z",
            "owner": "revskill10",
            "repo": "next-routes-middleware",
            "stars": 40
          }
        },
        {
          "children": [],
          "description": "Deploy serverless applications with ease.",
          "title": "Serverless Framework plugin for Next.js",
          "repo_info": {
            "archived": true,
            "language": "TypeScript",
            "last_commit": "2025-01-28T06:41:00Z",
            "owner": "danielcondemarin",
            "repo": "serverless-nextjs-plugin",
            "stars": 4476
          }
        },
        {
          "children": [],
          "description": "Deploy your application using Terraform",
          "title": "Terraform For Next.js",
          "repo_info": {
            "archived": true,
            "language": "JavaScript",
            "last_commit": "2023-07-20T17:43:12Z",
            "owner": "ematipico",
            "repo": "terraform-nextjs-plugin",
            "stars": 54
          }
        },
        {
          "children": [],
          "description": "Session middleware for Next.js",
          "title": "next-session",
          "repo_info": {
            "archived": false,
            "language": "TypeScript",
            "last_commit": "2024-05-23T06:21:26Z",
            "owner": "hoangvvo",
            "repo": "next-session",
            "stars": 358
          }
        },
        {
          "children": [],
          "description": "Next.js stateless session utility using signed and encrypted cookies to store data",
          "title": "next-iron-session",
          "repo_info": {
            "archived": false,
            "language": "TypeScript",
            "last_commit": "2026-02-12T18:37:49Z",
            "owner": "vvo",
            "repo": "next-iron-session",
            "stars": 4104
          }
        },
        {
          "children": [],
          "description": "Easily integrate , which helps you remove unused CSS from your bundle.",
          "title": "Next PurgeCSS",
          "repo_info": {
            "archived": false,
            "language": "JavaScript",
            "last_commit": "2020-03-24T12:34:04Z",
            "owner": "lucleray",
            "repo": "next-purgecss",
            "stars": 137
          }
        },
        {
          "children": [],
          "description": "Zero config PWA plugin for Next.js with workbox",
          "title": "Next PWA",
          "repo_info": {
            "archived": false,
            "language": "JavaScript",
            "last_commit": "2024-07-27T00:29:09Z",
            "owner": "shadowwalker",
            "repo": "next-pwa",
            "stars": 4089
          }
        },
        {
          "children": [],
          "description": "Run any of Express middlewares on Next.js without polluting native objects.",
          "title": "flow-middleware",
          "repo_info": {
            "archived": false,
            "language": "TypeScript",
            "last_commit": "2026-01-23T08:04:00Z",
            "owner": "piglovesyou",
            "repo": "flow-middleware",
            "stars": 15
          }
        },
        {
          "children": [],
          "description": "The Express/Connect-compatible router and middleware layer for Next.js.",
          "title": "next-connect",
          "repo_info": {
            "archived": false,
            "language": "TypeScript",
            "last_commit": "2024-02-15T06:39:41Z",
            "owner": "hoangvvo",
            "repo": "next-connect",
            "stars": 1660
          }
        },
        {
          "children": [],
          "description": "a plugin for embedding optimized images with ease.",
          "title": "next-img",
          "repo_info": {
            "archived": false,
            "language": "JavaScript",
            "last_commit": "2026-01-26T17:45:38Z",
            "owner": "humaans",
            "repo": "next-img",
            "stars": 277
          }
        },
        {
          "children": [],
          "description": "Easy authentication for Next.js and Serverless",
          "title": "next-auth",
          "repo_info": {
            "archived": false,
            "language": "TypeScript",
            "last_commit": "2026-02-07T21:40:57Z",
            "owner": "iaincollins",
            "repo": "next-auth",
            "stars": 28071
          }
        },
        {
          "children": [],
          "description": "Effortless deployment to AWS and GitHub Pages.",
          "title": "next-deploy",
          "repo_info": {
            "archived": true,
            "language": "TypeScript",
            "last_commit": "2024-07-17T21:29:58Z",
            "owner": "lone-cloud",
            "repo": "next-deploy",
            "stars": 49
          }
        },
        {
          "children": [],
          "description": "Validate Next.js API Routes, with .",
          "title": "next-joi",
          "repo_info": {
            "archived": false,
            "language": "TypeScript",
            "last_commit": "2022-06-12T18:07:24Z",
            "owner": "codecoolture",
            "repo": "next-joi",
            "stars": 109
          }
        },
        {
          "children": [],
          "description": "Next.js plugin to transpile code from node_modules. Useful for monorepos.",
          "title": "next-transpile-modules",
          "repo_info": {
            "archived": true,
            "language": "JavaScript",
            "last_commit": "2023-07-24T11:43:57Z",
            "owner": "martpie",
            "repo": "next-transpile-modules",
            "stars": 1130
          }
        },
        {
          "children": [],
          "description": "Next.js extension to visually build landing pages locally.",
          "title": "Destack for Next.js",
          "repo_info": {
            "archived": false,
            "language": "HTML",
            "last_commit": "2024-10-22T23:55:12Z",
            "owner": "liveduo",
            "repo": "destack",
            "stars": 1842
          }
        },
        {
          "children": [],
          "description": "React hooks and Next.js API routes that make it super easy to add Sign-In with Ethereum to your app.",
          "title": "UseSIWE",
          "repo_info": {
            "archived": false,
            "language": "TypeScript",
            "last_commit": "2023-10-28T07:23:00Z",
            "owner": "random-bits-studio",
            "repo": "use-siwe",
            "stars": 24
          }
        },
        {
          "children": [],
          "description": "Stop configuring ENV variables in CI/CD, use a cloud-native approach.",
          "title": "Runtime Environment Variables for Next.js"
        },
        {
          "children": [],
          "description": "Easily add Google Tag Manager to Next 13 and up.",
          "title": "next-google-tag-manager",
          "repo_info": {
            "archived": false,
            "language": "TypeScript",
            "last_commit": "2023-12-01T01:52:52Z",
            "owner": "XD2Sketch",
            "repo": "next-google-tag-manager",
            "stars": 48
          }
        },
        {
          "children": [],
          "description": "Decorators to create typed Next.js API routes, with easy request validation and transformation.",
          "title": "next-api-decorators",
          "repo_info": {
            "archived": false,
            "language": "TypeScript",
            "last_commit": "2024-04-05T06:54:24Z",
            "owner": "storyofams",
            "repo": "next-api-decorators",
            "stars": 425
          }
        },
        {
          "children": [],
          "description": "The AI Toolkit for TypeScript. Build AI-powered applications with React, Next.js, Vue, Svelte, and Node.js.",
          "title": "Vercel AI SDK",
          "repo_info": {
            "archived": false,
            "language": "TypeScript",
            "last_commit": "2026-02-13T04:05:53Z",
            "owner": "vercel",
            "repo": "ai",
            "stars": 21721
          }
        },
        {
          "children": [],
          "description": "React UI + elegant infrastructure for AI Copilots, AI chatbots, and in-app AI agents in your Next.js apps.",
          "title": "CopilotKit",
          "repo_info": {
            "archived": false,
            "language": "TypeScript",
            "last_commit": "2026-02-13T01:57:02Z",
            "owner": "CopilotKit",
            "repo": "CopilotKit",
            "stars": 28734
          }
        },
        {
          "children": [],
          "description": "Dynamic OG image generation API for Next.js apps, powered by Cloudflare Workers.",
          "title": "ShotOG",
          "repo_info": {
            "archived": false,
            "language": "TypeScript",
            "last_commit": "2026-02-12T02:45:02Z",
            "owner": "nicepkg",
            "repo": "shotog",
            "stars": 2
          }
        }
      ],
      "title": "Extensions"
    },
    {
      "description": "",
      "items": [
        {
          "children": [],
          "description": "An open source alternative to Thinkific, Teachable etc.",
          "title": "CourseLit",
          "repo_info": {
            "archived": false,
            "language": "TypeScript",
            "last_commit": "2026-02-12T16:36:45Z",
            "owner": "codelit",
            "repo": "courselit",
            "stars": 1109
          }
        },
        {
          "children": [],
          "description": "An open source social media application.",
          "title": "Feednext",
          "repo_info": {
            "archived": true,
            "language": "TypeScript",
            "last_commit": "2022-11-23T21:12:39Z",
            "owner": "feednext",
            "repo": "feednext",
            "stars": 321
          }
        },
        {
          "children": [],
          "description": "Simple Next.js application that showcases Game of Thrones Characters.",
          "title": "NextJS GOT",
          "repo_info": {
            "archived": false,
            "language": "JavaScript",
            "last_commit": "2017-12-21T23:34:43Z",
            "owner": "auth0-blog",
            "repo": "nextjs-got",
            "stars": 32
          }
        },
        {
          "children": [],
          "description": "Mindfulness community - React, GraphQL, Next.js.",
          "title": "Relate",
          "repo_info": {
            "archived": true,
            "language": "JavaScript",
            "last_commit": "2024-05-10T06:44:02Z",
            "owner": "RelateNow",
            "repo": "relate",
            "stars": 334
          }
        },
        {
          "children": [],
          "description": "One password, right way.",
          "title": "Password",
          "repo_info": {
            "archived": false,
            "language": "JavaScript",
            "last_commit": "2020-03-31T05:15:17Z",
            "owner": "dotcypress",
            "repo": "password",
            "stars": 119
          }
        },
        {
          "children": [],
          "description": "Todo list written in Next.js.",
          "title": "Next Todos",
          "repo_info": {
            "archived": false,
            "language": "JavaScript",
            "last_commit": "2023-07-22T16:59:29Z",
            "owner": "lipp",
            "repo": "next-todos",
            "stars": 132
          }
        },
        {
          "children": [],
          "description": "Another Hacker News written in Next.js.",
          "title": "Hacker News",
          "repo_info": {
            "archived": false,
            "language": "JavaScript",
            "last_commit": "2016-11-28T08:00:46Z",
            "owner": "lipp",
            "repo": "hackernews",
            "stars": 47
          }
        },
        {
          "children": [],
          "description": "Jet and Next.js powered Chat demo.",
          "title": "Jet Chat",
          "repo_info": {
            "archived": false,
            "language": "JavaScript",
            "last_commit": "2017-02-23T10:36:37Z",
            "owner": "lipp",
            "repo": "jet-chat",
            "stars": 10
          }
        },
        {
          "children": [],
          "description": "Sample Next.js v2 app for showing off its capabilities.",
          "title": "Nextgram",
          "repo_info": {
            "archived": false,
            "language": "JavaScript",
            "last_commit": "2017-07-15T22:45:40Z",
            "owner": "arunoda",
            "repo": "nextgram",
            "stars": 51
          }
        },
        {
          "children": [],
          "description": "Blog built by a Next.js core maintainer.",
          "title": "Rauchg Blog",
          "repo_info": {
            "archived": false,
            "language": "MDX",
            "last_commit": "2026-02-09T20:29:13Z",
            "owner": "rauchg",
            "repo": "blog",
            "stars": 1393
          }
        },
        {
          "children": [],
          "description": "JsonPlaceholder sample app made with Next.js.",
          "title": "Next JPH",
          "repo_info": {
            "archived": false,
            "language": "JavaScript",
            "last_commit": "2017-03-17T22:39:37Z",
            "owner": "renatorib",
            "repo": "next-jph",
            "stars": 36
          }
        },
        {
          "children": [],
          "description": "HTML mailto's made easy.",
          "title": "Mailto",
          "repo_info": {
            "archived": false,
            "language": "JavaScript",
            "last_commit": "2024-06-16T11:24:49Z",
            "owner": "dawsbot",
            "repo": "mailto",
            "stars": 224
          }
        },
        {
          "children": [],
          "description": "The task management app to rule them all.",
          "title": "Plate",
          "repo_info": {
            "archived": false,
            "language": "TypeScript",
            "last_commit": "2023-01-06T02:17:34Z",
            "owner": "knipferrc",
            "repo": "plate",
            "stars": 50
          }
        },
        {
          "children": [],
          "description": "Create your own team dashboard with custom widgets.",
          "title": "Dashboard",
          "repo_info": {
            "archived": false,
            "language": "JavaScript",
            "last_commit": "2023-05-03T04:58:01Z",
            "owner": "danielbayerlein",
            "repo": "dashboard",
            "stars": 1331
          }
        },
        {
          "children": [],
          "description": "A torrent client to search, stream and download torrents.",
          "title": "Snape",
          "repo_info": {
            "archived": false,
            "language": "TypeScript",
            "last_commit": "2021-02-23T13:39:11Z",
            "owner": "ritz078",
            "repo": "snape",
            "stars": 847
          }
        },
        {
          "children": [],
          "description": "Converts trello data into fast read information.",
          "title": "Trello Resume",
          "repo_info": {
            "archived": false,
            "language": "JavaScript",
            "last_commit": "2017-07-24T01:26:17Z",
            "owner": "juliandavidmr",
            "repo": "TrelloResume",
            "stars": 16
          }
        },
        {
          "children": [],
          "description": "Server authentication, prevent render before validation.",
          "title": "Server Authentication with JWT",
          "repo_info": {
            "archived": false,
            "language": "JavaScript",
            "last_commit": "2023-01-04T21:36:09Z",
            "owner": "estrada9166",
            "repo": "server-authentication-next.js",
            "stars": 107
          }
        },
        {
          "children": [],
          "description": "personal homepage built with Next.js, GraphQL, Docker and Kubernetes. Uses apollo client, react-intl, styled-components and recompose. Docker images are automatically built by GitLab CI.",
          "title": "Alexander Kachkaev’s website"
        },
        {
          "children": [],
          "description": "Cookie handler with server render, access the cookie before render.",
          "title": "Cookie handler with server render",
          "repo_info": {
            "archived": false,
            "language": "JavaScript",
            "last_commit": "2018-01-26T01:57:08Z",
            "owner": "estrada9166",
            "repo": "cookie-handler-next.js",
            "stars": 15
          }
        },
        {
          "children": [],
          "description": "A Next.js App use gank-api, mobx and antd",
          "title": "Gank",
          "repo_info": {
            "archived": false,
            "language": "JavaScript",
            "last_commit": "2023-01-07T04:02:14Z",
            "owner": "OrangeXC",
            "repo": "gank",
            "stars": 130
          }
        },
        {
          "children": [],
          "description": null,
          "title": "Decoupled CMS example with GraphQL and Next.js",
          "repo_info": {
            "archived": false,
            "language": "JavaScript",
            "last_commit": "2018-12-21T08:56:12Z",
            "owner": "janit",
            "repo": "decoupled-cms-nextjs-graphql",
            "stars": 30
          }
        },
        {
          "children": [],
          "description": "Mozilla VR Home",
          "title": "Mozilla VR Home"
        },
        {
          "children": [],
          "description": "Elton John's Website",
          "title": "Elton John's website"
        },
        {
          "children": [],
          "description": "IOTA Market Place",
          "title": "IOTA's Data Market Place"
        },
        {
          "children": [],
          "description": "Magic Leap",
          "title": "magicleap.com"
        },
        {
          "children": [],
          "description": "NPM's Search Page",
          "title": "NPM.js Search Page"
        },
        {
          "children": [],
          "description": "Docker Success Center",
          "title": "Docker Success Center"
        },
        {
          "children": [],
          "description": "German Legal Information System licensed under GPLv3.",
          "title": "Urteile & Gesetze",
          "repo_info": {
            "archived": false,
            "language": "JavaScript",
            "last_commit": "2025-03-24T22:32:27Z",
            "owner": "neo-search",
            "repo": "urteile-gesetze-web",
            "stars": 18
          }
        },
        {
          "children": [],
          "description": "TikTok's Home Page",
          "title": "TikTok's HomePage"
        },
        {
          "children": [],
          "description": "npm jump to 🐸 (package navigation shortcuts you dreamed about). Partially statically-rendered, partially deployed as lambda. Automatically updated on each commit to the , thanks to Now integration.",
          "title": "njt.now.sh",
          "repo_info": {
            "archived": false,
            "language": "TypeScript",
            "last_commit": "2026-02-12T14:05:51Z",
            "owner": "kachkaev",
            "repo": "njt",
            "stars": 318
          }
        },
        {
          "children": [],
          "description": "A text case converter.",
          "title": "caseconverter.pro"
        },
        {
          "children": [],
          "description": "Bookmark manager on steroid built with NextJs / Auth0 / Apollo Tools / Prisma2",
          "title": "Tottem",
          "repo_info": {
            "archived": false,
            "language": "TypeScript",
            "last_commit": "2023-01-24T01:15:30Z",
            "owner": "poulainv",
            "repo": "tottem",
            "stars": 979
          }
        },
        {
          "children": [],
          "description": "A fun way to discover relaxing virtual experiences. Next.js + Chakra UI + MySQL hosted on Vercel.",
          "title": "Slow TV Map"
        },
        {
          "children": [],
          "description": "Twitter clone built with Next.js + T3 Stack + NextAuth + Supabase + Prisma.",
          "title": "Twitter Clone",
          "repo_info": {
            "archived": true,
            "language": "TypeScript",
            "last_commit": "2023-08-17T19:09:54Z",
            "owner": "AlandSleman",
            "repo": "t3-twitter-clone",
            "stars": 190
          }
        },
        {
          "children": [],
          "description": "An example app built using Next.js 13 server components.",
          "title": "Taxonomy",
          "repo_info": {
            "archived": false,
            "language": "TypeScript",
            "last_commit": "2024-08-14T20:42:51Z",
            "owner": "shadcn",
            "repo": "taxonomy",
            "stars": 19157
          }
        },
        {
          "children": [],
          "description": "Beautifully designed components that you can copy and paste into your apps.",
          "title": "shadcn/ui",
          "repo_info": {
            "archived": false,
            "language": "TypeScript",
            "last_commit": "2026-02-12T07:37:43Z",
            "owner": "shadcn",
            "repo": "ui",
            "stars": 106556
          }
        },
        {
          "children": [],
          "description": "A Simple File Storage Service Built with Go and Next.js.",
          "title": "StorageBox",
          "repo_info": {
            "archived": true,
            "language": "TypeScript",
            "last_commit": "2023-10-18T09:44:41Z",
            "owner": "AlandSleman",
            "repo": "StorageBox",
            "stars": 23
          }
        },
        {
          "children": [],
          "description": "AI-powered workspace for teams with real-time collaboration, AI agents, project management, and workflow automation.",
          "title": "Taskade"
        }
      ],
      "title": "Apps"
    },
    {
      "description": "Found an awesome package, article, blog, video etc.? Send me a pull request! Just follow the guidelines. Thank you!\nCheck out my blog or say hi on Twitter.",
      "items": [],
      "title": "Contributing"
    },
    {
      "description": "",
      "items": [],
      "title": "License"
    }
  ],
  "metadata": {
    "last_updated": "2026-02-13T04:13:43.533Z",
    "original_repository": "unicodeveloper/awesome-nextjs",
    "source_repository": "v1nvn/enhansome-nextjs",
    "source_repository_description": null,
    "title": "Awesome Next.js with stars"
  }
}